pygeolocate/__init__.py
pygeolocate/countries_csv.py
pygeolocate/pygeolocate.py
pygeolocate/structures.py
pygeolocate-1.0.11.dist-info/LICENSE
pygeolocate-1.0.11.dist-info/METADATA
pygeolocate-1.0.11.dist-info/WHEEL
pygeolocate-1.0.11.dist-info/top_level.txt
pygeolocate-1.0.11.dist-info/RECORD
