Metadata-Version: 2.1
Name: pygeolocate
Version: 1.0.11
Summary: An easy way to find a countries coordinates by name
Home-page: https://github.com/Scrumpyy/pygeolocate
Author: Isabelle
Author-email: scrumpy@weeb.email
License: MIT
Project-URL: Bug Tracker, https://github.com/Scrumpyy/pygeolocate/issues
Keywords: location,geolocation,geolocate
Platform: UNKNOWN
Classifier: Development Status :: 5 - Production/Stable
Classifier: Intended Audience :: Developers
Classifier: License :: OSI Approved :: MIT License
Classifier: Programming Language :: Python :: 3.6
